{
  "1": {
    "ID": 1,
    "AnnotationLocMeta": {
      "InKey": "Annotation_1",
      "InTextLiteral": "发布违规信息",
      "InNamespace": "lobby_TBBanReason"
    },
    "Tips": "发布违规信息"
  },
  "2": {
    "ID": 2,
    "AnnotationLocMeta": {
      "InKey": "Annotation_2",
      "InTextLiteral": "个人资料违规",
      "InNamespace": "lobby_TBBanReason"
    },
    "Tips": "个人资料违规"
  },
  "3": {
    "ID": 3,
    "AnnotationLocMeta": {
      "InKey": "Annotation_3",
      "InTextLiteral": "恶意游戏行为",
      "InNamespace": "lobby_TBBanReason"
    },
    "Tips": "恶意游戏行为"
  },
  "4": {
    "ID": 4,
    "AnnotationLocMeta": {
      "InKey": "Annotation_4",
      "InTextLiteral": "使用作弊工具",
      "InNamespace": "lobby_TBBanReason"
    },
    "Tips": "使用作弊工具"
  },
  "5": {
    "ID": 5,
    "AnnotationLocMeta": {
      "InKey": "Annotation_5",
      "InTextLiteral": "恶意游戏行为",
      "InNamespace": "lobby_TBBanReason"
    },
    "Tips": "恶意游戏行为"
  }
}